images_upload_cli/__init__.py
images_upload_cli/__main__.py
images_upload_cli/_cli.py
images_upload_cli/image.py
images_upload_cli/logger.py
images_upload_cli/main.py
images_upload_cli/upload.py
images_upload_cli/util.py
images_upload_cli-3.0.6.dist-info/METADATA
images_upload_cli-3.0.6.dist-info/WHEEL
images_upload_cli-3.0.6.dist-info/entry_points.txt
images_upload_cli-3.0.6.dist-info/licenses/LICENSE
images_upload_cli-3.0.6.dist-info/RECORD
