Metadata-Version: 2.4
Name: images-upload-cli
Version: 3.0.6
Summary: Upload images via APIs
Project-URL: Repository, https://github.com/deadnews/images-upload-cli
Project-URL: Changelog, https://github.com/deadnews/images-upload-cli/CHANGELOG.md
Project-URL: Documentation, https://deadnews.github.io/images-upload-cli
Author-email: deadnews <deadnewsgit@gmail.com>
License-Expression: MIT
License-File: LICENSE
Keywords: cli,image-upload,imgur,upload-images,upload-pictures
Classifier: Environment :: Console
Classifier: Operating System :: OS Independent
Requires-Python: >=3.10
Requires-Dist: click>=8.1.7
Requires-Dist: httpx>=0.28.0
Requires-Dist: loguru>=0.7.2
Requires-Dist: pillow>=11.0.0
Requires-Dist: pyperclip>=1.9.0
Requires-Dist: python-dotenv>=1.0.1
Requires-Dist: rich>=14.0.0
